teddynote_parser_client/__init__.py
teddynote_parser_client/__main__.py
teddynote_parser_client/cli.py
teddynote_parser_client/client.py
teddynote_parser_client-0.0.2.dist-info/LICENSE
teddynote_parser_client-0.0.2.dist-info/METADATA
teddynote_parser_client-0.0.2.dist-info/WHEEL
teddynote_parser_client-0.0.2.dist-info/entry_points.txt
teddynote_parser_client-0.0.2.dist-info/top_level.txt
teddynote_parser_client-0.0.2.dist-info/RECORD
