Metadata-Version: 2.2
Name: teddynote-parser-client
Version: 0.0.2
Summary: TeddyNote Parser API 클라이언트 라이브러리
Author-email: teddylee777 <teddylee777@gmail.com>
License: MIT
Project-URL: Homepage, https://github.com/teddylee777/teddynote-parser-api-client
Project-URL: Bug Tracker, https://github.com/teddylee777/teddynote-parser-api-client/issues
Keywords: pdf,parser,api,client,teddynote
Classifier: Programming Language :: Python :: 3
Classifier: Programming Language :: Python :: 3.7
Classifier: Programming Language :: Python :: 3.8
Classifier: Programming Language :: Python :: 3.9
Classifier: Programming Language :: Python :: 3.10
Classifier: Programming Language :: Python :: 3.11
Classifier: Programming Language :: Python :: 3.12
Classifier: Programming Language :: Python :: 3.13
Classifier: License :: OSI Approved :: MIT License
Classifier: Operating System :: OS Independent
Classifier: Topic :: Software Development :: Libraries :: Python Modules
Requires-Python: >=3.7
License-File: LICENSE
Requires-Dist: jupyter>=1.1.1
Requires-Dist: langchain>=0.0.27
Requires-Dist: notebook>=6.5.7
Requires-Dist: pandas>=1.1.5
Requires-Dist: python-dotenv>=0.21.1
Requires-Dist: requests>=2.25.0
Provides-Extra: dev
Requires-Dist: pytest>=7.0.0; extra == "dev"
Requires-Dist: black>=22.1.0; extra == "dev"
Requires-Dist: isort>=5.10.1; extra == "dev"
Requires-Dist: mypy>=0.942; extra == "dev"
Requires-Dist: ruff>=0.0.186; extra == "dev"
Requires-Dist: build>=0.8.0; extra == "dev"
Requires-Dist: twine>=4.0.0; extra == "dev"
